faceit/__init__.py
faceit/constants.py
faceit/exceptions.py
faceit/faceit.py
faceit/py.typed
faceit/types.py
faceit/utils.py
faceit/http/__init__.py
faceit/http/client.py
faceit/http/helpers.py
faceit/models/__init__.py
faceit/models/championships.py
faceit/models/item_page.py
faceit/models/custom_types/__init__.py
faceit/models/custom_types/common.py
faceit/models/custom_types/faceit_uuid.py
faceit/models/players/__init__.py
faceit/models/players/general.py
faceit/models/players/match.py
faceit/resources/__init__.py
faceit/resources/base.py
faceit/resources/pagination.py
faceit/resources/resource_aggregator.py
faceit/resources/data/__init__.py
faceit/resources/data/championships.py
faceit/resources/data/helpers.py
faceit/resources/data/leagues.py
faceit/resources/data/matches.py
faceit/resources/data/matchmakings.py
faceit/resources/data/players.py
faceit/resources/data/rankings.py
faceit/resources/data/teams.py
faceit-0.1.4.dist-info/METADATA
faceit-0.1.4.dist-info/WHEEL
faceit-0.1.4.dist-info/licenses/LICENSE
faceit-0.1.4.dist-info/RECORD
